README.md
setup.py
avilabs_plotter.egg-info/PKG-INFO
avilabs_plotter.egg-info/SOURCES.txt
avilabs_plotter.egg-info/dependency_links.txt
avilabs_plotter.egg-info/requires.txt
avilabs_plotter.egg-info/top_level.txt
plotter/__init__.py
plotter/axis.py
plotter/backend.py
plotter/chart.py
plotter/color.py
plotter/enums.py
plotter/font.py
plotter/frame.py
plotter/plot.py
plotter/singletons.py
plotter/version.py
plotter/backends/__init__.py
plotter/backends/matplotlib_backend.py
plotter/category/__init__.py
plotter/category/horizontal_bar.py
plotter/category/line.py
plotter/category/vertical_bar.py
plotter/images/__init__.py
plotter/images/grayscale_image.py
plotter/images/rgb_image.py
plotter/numeric/__init__.py
plotter/numeric/graph.py
plotter/numeric/scatter.py
plotter/numeric/stem.py