Metadata-Version: 2.1
Name: avilabs-plotter
Version: 1.1.0
Summary: Python plotting APIs
Home-page: https://gitlab.com/avilay/plotter
Author: Avilay Parekh
Author-email: avilay@gmail.com
License: MIT
Platform: UNKNOWN
